{
    "key": "group_5ed4c2bc78095",
    "title": "Section Properties",
    "fields": [
        {
            "key": "field_5ed4c2c043979",
            "label": "Layout",
            "name": "layout",
            "type": "select",
            "instructions": "",
            "required": 0,
            "conditional_logic": 0,
            "wrapper": {
                "width": "",
                "class": "",
                "id": ""
            },
            "choices": {
                "page_banner": "Page Banner",
                "full_width": "Full Width",
                "two_columns": "Two Columns",
                "row_content": "Row Content",
                "tiles": "Tiles",
                "slider": "Slider",
                "blog": "Blog"
            },
            "default_value": false,
            "allow_null": 0,
            "multiple": 0,
            "ui": 1,
            "ajax": 0,
            "return_format": "value",
            "placeholder": ""
        },
        {
            "key": "field_5ed4efc64795c",
            "label": "Page Banner",
            "name": "page_banner",
            "type": "group",
            "instructions": "",
            "required": 0,
            "conditional_logic": [
                [
                    {
                        "field": "field_5ed4c2c043979",
                        "operator": "==",
                        "value": "page_banner"
                    }
                ]
            ],
            "wrapper": {
                "width": "",
                "class": "",
                "id": ""
            },
            "layout": "block",
            "sub_fields": [
                {
                    "key": "field_5ed4c3da1eff9",
                    "label": "Page Banner",
                    "name": "page_banner",
                    "type": "clone",
                    "instructions": "",
                    "required": 0,
                    "conditional_logic": [
                        [
                            {
                                "field": "field_5ed4c2c043979",
                                "operator": "==",
                                "value": "page_banner"
                            }
                        ]
                    ],
                    "wrapper": {
                        "width": "",
                        "class": "",
                        "id": ""
                    },
                    "clone": [
                        "group_5cbda6d330d43"
                    ],
                    "display": "seamless",
                    "layout": "block",
                    "prefix_label": 0,
                    "prefix_name": 0
                }
            ]
        },
        {
            "key": "field_5ed4f08419ade",
            "label": "Full Width",
            "name": "full_width",
            "type": "group",
            "instructions": "",
            "required": 0,
            "conditional_logic": [
                [
                    {
                        "field": "field_5ed4c2c043979",
                        "operator": "==",
                        "value": "full_width"
                    }
                ]
            ],
            "wrapper": {
                "width": "",
                "class": "",
                "id": ""
            },
            "layout": "block",
            "sub_fields": [
                {
                    "key": "field_5ed4c4f90f673",
                    "label": "Full Width",
                    "name": "full_width",
                    "type": "clone",
                    "instructions": "",
                    "required": 0,
                    "conditional_logic": [
                        [
                            {
                                "field": "field_5ed4c2c043979",
                                "operator": "==",
                                "value": "full_width"
                            }
                        ]
                    ],
                    "wrapper": {
                        "width": "",
                        "class": "",
                        "id": ""
                    },
                    "clone": [
                        "group_5ce553dd81658"
                    ],
                    "display": "seamless",
                    "layout": "",
                    "prefix_label": 0,
                    "prefix_name": 0
                }
            ]
        },
        {
            "key": "field_5ed4f0fa19ae2",
            "label": "Two Columns",
            "name": "two_columns",
            "type": "group",
            "instructions": "",
            "required": 0,
            "conditional_logic": [
                [
                    {
                        "field": "field_5ed4c2c043979",
                        "operator": "==",
                        "value": "two_columns"
                    }
                ]
            ],
            "wrapper": {
                "width": "",
                "class": "",
                "id": ""
            },
            "layout": "block",
            "sub_fields": [
                {
                    "key": "field_5ed4c5250f674",
                    "label": "Two Columns",
                    "name": "two_columns",
                    "type": "clone",
                    "instructions": "",
                    "required": 0,
                    "conditional_logic": [
                        [
                            {
                                "field": "field_5ed4c2c043979",
                                "operator": "==",
                                "value": "two_columns"
                            }
                        ]
                    ],
                    "wrapper": {
                        "width": "",
                        "class": "",
                        "id": ""
                    },
                    "clone": [
                        "group_5d3252847f154"
                    ],
                    "display": "seamless",
                    "layout": "block",
                    "prefix_label": 0,
                    "prefix_name": 0
                }
            ]
        },
        {
            "key": "field_5ed4f0b919ae0",
            "label": "Row Content",
            "name": "row_content",
            "type": "group",
            "instructions": "",
            "required": 0,
            "conditional_logic": [
                [
                    {
                        "field": "field_5ed4c2c043979",
                        "operator": "==",
                        "value": "row_content"
                    }
                ]
            ],
            "wrapper": {
                "width": "",
                "class": "",
                "id": ""
            },
            "layout": "block",
            "sub_fields": [
                {
                    "key": "field_5ed4c5590f676",
                    "label": "Row Content",
                    "name": "row_content",
                    "type": "clone",
                    "instructions": "",
                    "required": 0,
                    "conditional_logic": [
                        [
                            {
                                "field": "field_5ed4c2c043979",
                                "operator": "==",
                                "value": "row_content"
                            }
                        ]
                    ],
                    "wrapper": {
                        "width": "",
                        "class": "",
                        "id": ""
                    },
                    "clone": [
                        "group_5cbda7ffd5b5f"
                    ],
                    "display": "seamless",
                    "layout": "",
                    "prefix_label": 0,
                    "prefix_name": 0
                }
            ]
        },
        {
            "key": "field_5ed4f13f19ae4",
            "label": "Tiles",
            "name": "tiles",
            "type": "group",
            "instructions": "",
            "required": 0,
            "conditional_logic": [
                [
                    {
                        "field": "field_5ed4c2c043979",
                        "operator": "==",
                        "value": "tiles"
                    }
                ]
            ],
            "wrapper": {
                "width": "",
                "class": "",
                "id": ""
            },
            "layout": "block",
            "sub_fields": [
                {
                    "key": "field_5ed4c5720f677",
                    "label": "Tiles",
                    "name": "tiles",
                    "type": "clone",
                    "instructions": "",
                    "required": 0,
                    "conditional_logic": [
                        [
                            {
                                "field": "field_5ed4c2c043979",
                                "operator": "==",
                                "value": "tiles"
                            }
                        ]
                    ],
                    "wrapper": {
                        "width": "",
                        "class": "",
                        "id": ""
                    },
                    "clone": [
                        "group_5cbda89b38c8d"
                    ],
                    "display": "seamless",
                    "layout": "",
                    "prefix_label": 0,
                    "prefix_name": 0
                }
            ]
        },
        {
            "key": "field_5ed4f15f19ae6",
            "label": "Slider",
            "name": "slider",
            "type": "group",
            "instructions": "",
            "required": 0,
            "conditional_logic": [
                [
                    {
                        "field": "field_5ed4c2c043979",
                        "operator": "==",
                        "value": "slider"
                    }
                ]
            ],
            "wrapper": {
                "width": "",
                "class": "",
                "id": ""
            },
            "layout": "block",
            "sub_fields": [
                {
                    "key": "field_5ed4c58a0f678",
                    "label": "Slider",
                    "name": "slider",
                    "type": "clone",
                    "instructions": "",
                    "required": 0,
                    "conditional_logic": [
                        [
                            {
                                "field": "field_5ed4c2c043979",
                                "operator": "==",
                                "value": "slider"
                            }
                        ]
                    ],
                    "wrapper": {
                        "width": "",
                        "class": "",
                        "id": ""
                    },
                    "clone": [
                        "group_5cbdab602b9b4"
                    ],
                    "display": "seamless",
                    "layout": "",
                    "prefix_label": 0,
                    "prefix_name": 0
                }
            ]
        },
        {
            "key": "field_5ed4f17919ae8",
            "label": "Blog",
            "name": "blog",
            "type": "group",
            "instructions": "",
            "required": 0,
            "conditional_logic": [
                [
                    {
                        "field": "field_5ed4c2c043979",
                        "operator": "==",
                        "value": "blog"
                    }
                ]
            ],
            "wrapper": {
                "width": "",
                "class": "",
                "id": ""
            },
            "layout": "block",
            "sub_fields": [
                {
                    "key": "field_5ed4c5a70f679",
                    "label": "Blog",
                    "name": "blog",
                    "type": "clone",
                    "instructions": "",
                    "required": 0,
                    "conditional_logic": [
                        [
                            {
                                "field": "field_5ed4c2c043979",
                                "operator": "==",
                                "value": "blog"
                            }
                        ]
                    ],
                    "wrapper": {
                        "width": "",
                        "class": "",
                        "id": ""
                    },
                    "clone": [
                        "group_5dba7a141c889"
                    ],
                    "display": "seamless",
                    "layout": "block",
                    "prefix_label": 0,
                    "prefix_name": 0
                }
            ]
        }
    ],
    "location": [
        [
            {
                "param": "post_type",
                "operator": "==",
                "value": "section"
            }
        ]
    ],
    "menu_order": 0,
    "position": "acf_after_title",
    "style": "default",
    "label_placement": "top",
    "instruction_placement": "label",
    "hide_on_screen": [
        "the_content",
        "excerpt"
    ],
    "active": true,
    "description": "",
    "modified": 1626686787
}